fast_carpenter/__init__.py
fast_carpenter/__main__.py
fast_carpenter/bookkeeping.py
fast_carpenter/expressions.py
fast_carpenter/tree_adapter.py
fast_carpenter/utils.py
fast_carpenter/version.py
fast_carpenter/weights.py
fast_carpenter/backends/__init__.py
fast_carpenter/backends/_alphatwirl.py
fast_carpenter/backends/coffea.py
fast_carpenter/data_import/__init__.py
fast_carpenter/data_import/_base.py
fast_carpenter/data_import/_uproot3.py
fast_carpenter/data_import/_uproot4.py
fast_carpenter/define/__init__.py
fast_carpenter/define/reductions.py
fast_carpenter/define/systematics.py
fast_carpenter/define/variables.py
fast_carpenter/selection/__init__.py
fast_carpenter/selection/filters.py
fast_carpenter/selection/stage.py
fast_carpenter/summary/__init__.py
fast_carpenter/summary/aghast.py
fast_carpenter/summary/binned_dataframe.py
fast_carpenter/summary/binning_config.py
fast_carpenter/summary/event_level_dataframe.py
fast_carpenter/summary/import_aghast.py
fast_carpenter/testing/__init__.py
fast_carpenter-0.23.0.dist-info/licenses/LICENSE
fast_carpenter-0.23.0.dist-info/METADATA
fast_carpenter-0.23.0.dist-info/WHEEL
fast_carpenter-0.23.0.dist-info/entry_points.txt
fast_carpenter-0.23.0.dist-info/top_level.txt
fast_carpenter-0.23.0.dist-info/zip-safe
fast_carpenter-0.23.0.dist-info/RECORD
