Metadata-Version: 2.4
Name: fast-carpenter
Version: 0.23.0
Summary: F.A.S.T. package for summarizing ROOT TTrees
Home-page: https://github.com/FAST-HEP/fast-carpenter
Author: Ben Krikler
Author-email: fast-hep@cern.ch
License: Apache Software License 2.0
Keywords: ROOT,pandas,analysis,particle physics,HEP,F.A.S.T
Classifier: Development Status :: 4 - Beta
Classifier: Intended Audience :: Developers
Classifier: License :: OSI Approved :: Apache Software License
Classifier: Natural Language :: English
Classifier: Programming Language :: Python :: 3
Classifier: Programming Language :: Python :: 3.6
Classifier: Programming Language :: Python :: 3.7
Classifier: Programming Language :: Python :: 3.8
Classifier: Programming Language :: Python :: 3.9
License-File: LICENSE
Requires-Dist: atuproot==0.1.13
Requires-Dist: atsge==0.2.1
Requires-Dist: atpbar==1.0.8
Requires-Dist: mantichora==0.9.7
Requires-Dist: alphatwirl==0.25.5
Requires-Dist: fast-flow>0.5.0
Requires-Dist: fast-curator
Requires-Dist: awkward
Requires-Dist: coffea==0.7.9
Requires-Dist: pandas>=1.1
Requires-Dist: numpy==1.22.0; python_version < "3.9"
Requires-Dist: numpy>=1.18.5; python_version > "3.8"
Requires-Dist: numexpr
Requires-Dist: typing-extensions>=4.1.1
Requires-Dist: uproot>=4.1.8
Requires-Dist: uproot3>=3.14.0
Dynamic: author
Dynamic: author-email
Dynamic: classifier
Dynamic: description
Dynamic: home-page
Dynamic: keywords
Dynamic: license
Dynamic: license-file
Dynamic: requires-dist
Dynamic: summary
